em_toolhub/__init__.py
em_toolhub/api_client.py
em_toolhub/api_response.py
em_toolhub/configuration.py
em_toolhub/exceptions.py
em_toolhub/py.typed
em_toolhub/rest.py
em_toolhub/api/__init__.py
em_toolhub/api/files_api.py
em_toolhub/api/surveys_api.py
em_toolhub/api/wellbores_api.py
em_toolhub/api/wells_api.py
em_toolhub/models/__init__.py
em_toolhub/models/create_survey201_response_body.py
em_toolhub/models/create_survey201_response_body_data.py
em_toolhub/models/create_survey201_response_body_data_corrections_inner.py
em_toolhub/models/create_survey201_response_body_data_raw.py
em_toolhub/models/create_survey201_response_body_meta.py
em_toolhub/models/create_survey400_response_body.py
em_toolhub/models/create_survey400_response_body_error.py
em_toolhub/models/create_survey401_response_body.py
em_toolhub/models/create_survey404_response_body.py
em_toolhub/models/create_survey500_response_body.py
em_toolhub/models/create_survey_request_body.py
em_toolhub/models/create_survey_request_body_raw.py
em_toolhub/models/create_wellbore201_response_body.py
em_toolhub/models/create_wellbore201_response_body_data.py
em_toolhub/models/create_wellbore400_response_body.py
em_toolhub/models/create_wellbore401_response_body.py
em_toolhub/models/create_wellbore500_response_body.py
em_toolhub/models/create_wellbore_request_body.py
em_toolhub/models/delete_file401_response_body.py
em_toolhub/models/delete_file404_response_body.py
em_toolhub/models/delete_file500_response_body.py
em_toolhub/models/delete_survey200_response_body.py
em_toolhub/models/delete_survey200_response_body_data.py
em_toolhub/models/delete_survey401_response_body.py
em_toolhub/models/delete_survey404_response_body.py
em_toolhub/models/delete_survey500_response_body.py
em_toolhub/models/delete_wellbore200_response_body.py
em_toolhub/models/delete_wellbore400_response_body.py
em_toolhub/models/delete_wellbore401_response_body.py
em_toolhub/models/delete_wellbore404_response_body.py
em_toolhub-0.1.2.dist-info/METADATA
em_toolhub-0.1.2.dist-info/WHEEL
em_toolhub-0.1.2.dist-info/top_level.txt
em_toolhub-0.1.2.dist-info/RECORD
