Metadata-Version: 2.4
Name: em_toolhub
Version: 0.1.2
Summary: ToolHub Customer API
Home-page: 
Author: Erdos Miller
Author-email: Erdos Miller <team@openapitools.org>
Project-URL: Repository, https://github.com/Erdos-Miller/repo
Keywords: OpenAPI,OpenAPI-Generator,ToolHub Customer API
Requires-Python: >=3.9
Requires-Dist: urllib3<3.0.0,>=2.1.0
Requires-Dist: python-dateutil>=2.8.2
Requires-Dist: pydantic>=2
Requires-Dist: typing-extensions>=4.7.1
Dynamic: author
